LICENSE
MANIFEST.in
README.rst
setup.py
plywood/__init__.py
plywood/__main__.py
plywood/element.py
plywood/env.py
plywood/exceptions.py
plywood/grammar.py
plywood/operators.py
plywood/run.py
plywood/runtime.py
plywood/scope.py
plywood/util.py
plywood/values.py
plywood.egg-info/PKG-INFO
plywood.egg-info/SOURCES.txt
plywood.egg-info/dependency_links.txt
plywood.egg-info/entry_points.txt
plywood.egg-info/pbr.json
plywood.egg-info/requires.txt
plywood.egg-info/top_level.txt
plywood/plugins/__init__.py
plywood/plugins/_break.py
plywood/plugins/_def.py
plywood/plugins/_for.py
plywood/plugins/_if.py
plywood/plugins/_import.py
plywood/plugins/_while.py
plywood/plugins/additions.py
plywood/plugins/constants.py
plywood/plugins/date.py
plywood/plugins/doctype.py
plywood/plugins/empty.py
plywood/plugins/entitize.py
plywood/plugins/extends.py
plywood/plugins/html.py
plywood/plugins/ieif.py
plywood/plugins/include.py
plywood/plugins/markdown.py
plywood/plugins/sys.py
plywood/plugins/tags.py
plywood/plugins/types.py
test/__init__.py
test/test_additions.py
test/test_assign.py
test/test_auto_product.py
test/test_def.py
test/test_dict.py
test/test_example.py
test/test_extends.py
test/test_for.py
test/test_get_value.py
test/test_ieif.py
test/test_if.py
test/test_import.py
test/test_include.py
test/test_interpolation.py
test/test_operators.py
test/test_plywood.py
test/test_stacktrace_output.py
test/test_stacktrace_syntax.py
test/test_syntax.py
test/test_variables.py
test/test_while.py
test/test_xml.py