Metadata-Version: 1.2
Name: plywood
Version: 2.1.0
Summary: A template language grammar inspired by the Python code aesthetic
Home-page: https://github.com/colinta/plywood
Author: Colin T.A. Gray
Author-email: colinta@gmail.com
License: BSD
Keywords: plywood template language
Platform: any
Classifier: Programming Language :: Python
Classifier: Programming Language :: Python :: 3
Classifier: Development Status :: 4 - Beta
Classifier: Environment :: Console
Classifier: License :: OSI Approved :: BSD License
Classifier: Operating System :: OS Independent
Classifier: Intended Audience :: End Users/Desktop
Classifier: Intended Audience :: Developers
Classifier: Topic :: Text Processing
Classifier: Topic :: Text Processing :: General
Classifier: Topic :: Text Processing :: Markup
Classifier: Topic :: Internet
Requires-Python: >3.0.0
